ropon/__init__.py
ropon/apis/filter.py
ropon/apis/game/filter.py
ropon/apis/game/badges/__init__.py
ropon/apis/game/info/__init__.py
ropon/apis/game/universe/__init__.py
ropon/apis/gamepass/__init__.py
ropon/apis/groups/filter.py
ropon/apis/groups/info/__init__.py
ropon/apis/groups/search/__init__.py
ropon/apis/groups/wall/__init__.py
ropon/apis/players/filter.py
ropon/apis/players/avatar/__init__.py
ropon/apis/players/badge/__init__.py
ropon/apis/players/connection/__init__.py
ropon/apis/players/game/__init__.py
ropon/apis/players/group/__init__.py
ropon/apis/players/info/__init__.py
ropon/apis/players/inventory/__init__.py
ropon/apis/thumbnails/filter.py
ropon/apis/thumbnails/assets/__init__.py
ropon/apis/thumbnails/avatar/__init__.py
ropon/apis/thumbnails/game/__init__.py
ropon-0.1.2.dist-info/METADATA
ropon-0.1.2.dist-info/WHEEL
ropon-0.1.2.dist-info/licenses/LICENSE
ropon-0.1.2.dist-info/RECORD
