Metadata-Version: 2.4
Name: ropon
Version: 0.1.2
Summary: A really simple and **very cool™** roblox api helper lib
License: MIT
License-File: LICENSE
Requires-Python: >=3.10
